PdfSplitter/Splitter.py
PdfSplitter/__init__.py
S3PdfSplitter-1.0.7.dist-info/METADATA
S3PdfSplitter-1.0.7.dist-info/RECORD
S3PdfSplitter-1.0.7.dist-info/WHEEL
S3PdfSplitter-1.0.7.dist-info/top_level.txt
