Metadata-Version: 2.1
Name: S3PdfSplitter
Version: 1.0.7
Summary: Splitter de fichiers pdfs sur S3
Home-page: https://github.com/Nydareld/S3PdfSplitter
Author: Théo "Nydareld" Guerin
Author-email: theo.guerin.pro@gmail.com
License: UNKNOWN
Platform: UNKNOWN
Classifier: Programming Language :: Python :: 3.5
Classifier: Programming Language :: Python :: 3.6
Classifier: Programming Language :: Python :: 3.7
Classifier: License :: OSI Approved :: MIT License
Classifier: Operating System :: OS Independent
